{
  "project_info": {
    "project_number": "237773436152",
    "project_id": "mobileprogramming1-30ddc",
    "storage_bucket": "mobileprogramming1-30ddc.firebasestorage.app"
  },
  "client": [
    {
      "client_info": {
        "mobilesdk_app_id": "1:237773436152:android:932b9a07a97d8449a6370d",
        "android_client_info": {
          "package_name": "com.example.mobileprogramming"
        }
      },
      "oauth_client": [],
      "api_key": [
        {
          "current_key": "AIzaSyBXHXUpEh7OhPym-VrsjCHhAo1AG0LG-BM"
        }
      ],
      "services": {
        "appinvite_service": {
          "other_platform_oauth_client": []
        }
      }
    }
  ],
  "configuration_version": "1"
}